{
  "task_id": "GRPS-002",
  "verification_policy": {
    "requires_tests": true,
    "requires_red_evidence": true,
    "requires_seeded_evidence": true
  },
  "project_commands": {
    "typecheck": "cargo check -p but-authz --all-targets && cargo check -p but-api --all-targets",
    "lint": "cargo clippy -p but-authz --all-targets && cargo clippy -p but-api --all-targets",
    "test": "cargo test -p but-authz && cargo test -p but-api"
  },
  "requirements": [
    {
      "id": "AC-1",
      "verify": "cargo test -p but-api self_add_to_maintainers_on_feature_head_still_denied_merge"
    },
    {
      "id": "AC-2",
      "verify": "cargo test -p but-api landed_membership_clears_merge_authority_step"
    },
    {
      "id": "AC-3",
      "verify": "cargo test -p but-authz self_grant_admin_inert_until_landed"
    },
    {
      "id": "AC-4",
      "verify": "cargo test -p but-authz membership_read_only_from_target_ref"
    },
    {
      "id": "TC-1",
      "verify": "cargo test -p but-api self_add_to_maintainers_on_feature_head_still_denied_merge"
    },
    {
      "id": "TC-2",
      "verify": "cargo test -p but-api self_add_to_maintainers_on_feature_head_still_denied_merge"
    },
    {
      "id": "TC-3",
      "verify": "cargo test -p but-api landed_membership_clears_merge_authority_step"
    },
    {
      "id": "TC-4",
      "verify": "cargo test -p but-api landed_membership_clears_merge_authority_step"
    },
    {
      "id": "TC-5",
      "verify": "cargo test -p but-authz self_grant_admin_inert_until_landed"
    },
    {
      "id": "TC-6",
      "verify": "cargo test -p but-authz self_grant_admin_inert_until_landed"
    },
    {
      "id": "TC-7",
      "verify": "cargo test -p but-authz membership_read_only_from_target_ref"
    },
    {
      "id": "TC-8",
      "verify": "cargo test -p but-authz membership_read_only_from_target_ref"
    }
  ]
}
